<?xml version="1.0" encoding="UTF-8"?>

<export>
	<file>
		<destination>system/workplace/resources/tools/publishqueue/buttons/cancel.png</destination>
		<type>image</type>
		<uuidstructure>fd3ae58a-7f9d-11db-a160-9362e1ae9c5d</uuidstructure>
		<uuidresource>fd3ae58b-7f9d-11db-a160-9362e1ae9c5d</uuidresource>
		<datelastmodified>Wed, 29 Nov 2006 11:37:46 GMT</datelastmodified>
		<userlastmodified>Admin</userlastmodified>
		<datecreated>Wed, 29 Nov 2006 11:37:27 GMT</datecreated>
		<usercreated>Admin</usercreated>
		<flags>0</flags>
		<properties>
			<property type="shared">
				<name>image.size</name>
				<value><![CDATA[w:20,h:20]]></value>
			</property>
		</properties>
		<relations/>
		<accesscontrol/>
	</file>
</export>
