<?xml version="1.0" encoding="UTF-8"?>

<export>
	<file>
		<destination>system/workplace/commons/style/new_admin.css</destination>
		<type>jsp</type>
		<uuidstructure>8291c4a4-11b7-11db-91cd-fdbae480bac9</uuidstructure>
		<uuidresource>f89039f1-7c11-11d9-a63e-8541f206766d</uuidresource>
		<datelastmodified>Mon, 27 May 2019 13:14:59 GMT</datelastmodified>
		<userlastmodified>Admin</userlastmodified>
		<datecreated>Mon, 27 Jun 2005 08:00:00 GMT</datecreated>
		<usercreated>Admin</usercreated>
		<flags>0</flags>
		<properties>
			<property type="shared">
				<name>export</name>
				<value><![CDATA[true]]></value>
			</property>
		</properties>
		<relations/>
		<accesscontrol/>
	</file>
</export>
