<?xml version="1.0" encoding="UTF-8"?>

<export>
	<file>
		<destination>system/modules/org.opencms.ade.upload/resources/upload/clear.cache.gif</destination>
		<type>image</type>
		<uuidstructure>6b17ce42-8f4e-11e3-810a-b1fec472a9fa</uuidstructure>
		<uuidresource>6b17f553-8f4e-11e3-810a-b1fec472a9fa</uuidresource>
		<datelastmodified>Thu, 06 Feb 2014 16:47:51 GMT</datelastmodified>
		<userlastmodified>Admin</userlastmodified>
		<datecreated>Thu, 06 Feb 2014 16:47:51 GMT</datecreated>
		<usercreated>Admin</usercreated>
		<flags>0</flags>
		<properties>
			<property type="shared">
				<name>image.size</name>
				<value><![CDATA[w:1,h:1]]></value>
			</property>
		</properties>
		<relations/>
		<accesscontrol/>
	</file>
</export>
