<?xml version="1.0" encoding="UTF-8"?>

<export>
	<file>
		<destination>system/workplace/resources/editors/fckeditor/editor/filemanager/browser/default/connectors/asp/config.asp</destination>
		<type>plain</type>
		<uuidstructure>378abe2e-03ac-11dc-b2d2-19a36bcdebf7</uuidstructure>
		<uuidresource>378abe2f-03ac-11dc-b2d2-19a36bcdebf7</uuidresource>
		<datelastmodified>Wed, 16 May 2007 12:53:52 GMT</datelastmodified>
		<userlastmodified>Admin</userlastmodified>
		<datecreated>Wed, 16 May 2007 12:51:51 GMT</datecreated>
		<usercreated>Admin</usercreated>
		<flags>0</flags>
		<properties/>
		<relations/>
		<accesscontrol/>
	</file>
</export>
