<?xml version="1.0" encoding="UTF-8"?>

<export>
	<file>
		<destination>system/workplace/resources/editors/tinymce/jscripts/tinymce/plugins/emoticons/img/smiley-innocent.gif</destination>
		<type>image</type>
		<uuidstructure>e8979665-279b-11e4-a042-9723befcacf3</uuidstructure>
		<uuidresource>e8979666-279b-11e4-a042-9723befcacf3</uuidresource>
		<datelastmodified>Tue, 19 Aug 2014 12:25:30 GMT</datelastmodified>
		<userlastmodified>Admin</userlastmodified>
		<datecreated>Tue, 19 Aug 2014 12:25:30 GMT</datecreated>
		<usercreated>Admin</usercreated>
		<flags>0</flags>
		<properties>
			<property>
				<name>Title</name>
				<value><![CDATA[smiley-innocent]]></value>
			</property>
			<property type="shared">
				<name>image.size</name>
				<value><![CDATA[w:18,h:18]]></value>
			</property>
		</properties>
		<relations/>
		<accesscontrol/>
	</file>
</export>
