<?xml version="1.0" encoding="UTF-8"?>

<export>
	<file>
		<destination>system/config/decoration</destination>
		<type>folder</type>
		<uuidstructure>726ff728-d14c-11e8-9434-b90516ef3600</uuidstructure>
		<datelastmodified>Mon, 16 Oct 2023 11:19:48 GMT</datelastmodified>
		<userlastmodified>Admin</userlastmodified>
		<datecreated>Tue, 08 Nov 2005 14:03:22 GMT</datecreated>
		<usercreated>Admin</usercreated>
		<flags>0</flags>
		<properties>
			<property>
				<name>Title</name>
				<value><![CDATA[HTML Decoration]]></value>
			</property>
			<property>
				<name>locale</name>
				<value><![CDATA[en]]></value>
			</property>
			<property>
				<name>locale-available</name>
				<value><![CDATA[en]]></value>
			</property>
		</properties>
		<relations/>
		<accesscontrol/>
	</file>
</export>
