<?xml version="1.0" encoding="UTF-8"?>

<export>
	<file>
		<destination>system/workplace/admin/searchindex/searchindex_search.jsp</destination>
		<type>jsp</type>
		<uuidstructure>cebb9a4e-11b7-11db-91cd-fdbae480bac9</uuidstructure>
		<uuidresource>c2ae5904-07e2-11da-9a85-0334e4183c08</uuidresource>
		<datelastmodified>Mon, 11 Dec 2006 15:32:18 GMT</datelastmodified>
		<userlastmodified>Admin</userlastmodified>
		<datecreated>Mon, 08 Aug 2005 08:02:27 GMT</datecreated>
		<usercreated>Admin</usercreated>
		<flags>0</flags>
		<properties>
			<property>
				<name>Description</name>
				<value><![CDATA[${key.GUI_GROUPS_SEARCHINDEX_TOOL_SEARCH_HELP_0}]]></value>
			</property>
			<property>
				<name>NavImage</name>
				<value><![CDATA[/tools/searchindex/icons/big/searchindex-search.png]]></value>
			</property>
			<property>
				<name>NavInfo</name>
				<value><![CDATA[${key.GUI_GROUPS_SEARCHINDEX_TOOL_EDIT_GROUP_0}]]></value>
			</property>
			<property>
				<name>NavPos</name>
				<value><![CDATA[2.0]]></value>
			</property>
			<property>
				<name>NavText</name>
				<value><![CDATA[${key.GUI_GROUPS_SEARCHINDEX_TOOL_SEARCH_0}]]></value>
			</property>
			<property>
				<name>Title</name>
				<value><![CDATA[New search index]]></value>
			</property>
			<property>
				<name>admintoolhandler-args</name>
				<value><![CDATA[params:action=initial&indexname=${param.indexname}|path:/searchindex/singleindex/search]]></value>
			</property>
			<property>
				<name>admintoolhandler-class</name>
				<value><![CDATA[org.opencms.workplace.tools.searchindex.CmsSearchToolHandler]]></value>
			</property>
			<property>
				<name>content-encoding</name>
				<value><![CDATA[utf-8]]></value>
			</property>
		</properties>
		<relations/>
		<accesscontrol/>
	</file>
</export>
