<?xml version="1.0" encoding="UTF-8"?>

<export>
	<file>
		<destination>system/workplace/resources/admin/images/border.gif</destination>
		<type>image</type>
		<uuidstructure>969a1814-11b7-11db-91cd-fdbae480bac9</uuidstructure>
		<uuidresource>7b217b1e-d0e5-11d9-ac67-b920ebfd9bc1</uuidresource>
		<datelastmodified>Wed, 19 Jul 2017 14:04:10 GMT</datelastmodified>
		<userlastmodified>Admin</userlastmodified>
		<datecreated>Mon, 27 Jun 2005 08:00:00 GMT</datecreated>
		<usercreated>Admin</usercreated>
		<flags>0</flags>
		<properties>
			<property type="shared">
				<name>image.size</name>
				<value><![CDATA[w:2,h:100]]></value>
			</property>
		</properties>
		<relations/>
		<accesscontrol/>
	</file>
</export>
