<?xml version="1.0" encoding="UTF-8"?>

<export>
	<file>
		<destination>system/workplace/commons</destination>
		<type>folder</type>
		<uuidstructure>e2dfba66-6c15-11ee-b8bd-cc483ab67959</uuidstructure>
		<datelastmodified>Mon, 16 Oct 2023 11:19:40 GMT</datelastmodified>
		<userlastmodified>Admin</userlastmodified>
		<datecreated>Mon, 16 Oct 2023 11:19:35 GMT</datecreated>
		<usercreated>Admin</usercreated>
		<flags>0</flags>
		<properties>
			<property>
				<name>cache</name>
				<value><![CDATA[false]]></value>
			</property>
		</properties>
		<relations/>
		<accesscontrol/>
	</file>
</export>
